bluetracker/__init__.py
bluetracker/__main__.py
bluetracker/config.toml
bluetracker/core.py
bluetracker/py.typed
bluetracker/helpers/__init__.py
bluetracker/helpers/mqtt_client.py
bluetracker/models/__init__.py
bluetracker/models/device.py
bluetracker/utils/__init__.py
bluetracker/utils/config.py
bluetracker/utils/homeassistant.py
bluetracker/utils/logging.py
bluetracker/utils/mqtt_messages.py
bluetracker_hass_mqtt-0.1.2.dist-info/LICENSE
bluetracker_hass_mqtt-0.1.2.dist-info/METADATA
bluetracker_hass_mqtt-0.1.2.dist-info/WHEEL
bluetracker_hass_mqtt-0.1.2.dist-info/entry_points.txt
bluetracker_hass_mqtt-0.1.2.dist-info/top_level.txt
bluetracker_hass_mqtt-0.1.2.dist-info/RECORD
