Metadata-Version: 2.1
Name: bluetracker-hass-mqtt
Version: 0.1.2
Summary: Monitor Bluetooth Classic devices and integrate them into Home Assistant via MQTT.
Author: essel-dev
License: MIT License
Project-URL: Bug Tracker, https://github.com/essel-dev/bluetracker-hass-mqtt/issues
Project-URL: Changelog, https://github.com/essel-dev/bluetracker-hass-mqtt/releases
Project-URL: Documentation, https://bluetracker-hass-mqtt.readthedocs.io/
Project-URL: GitHub, https://github.com/essel-dev/bluetracker-hass-mqtt
Keywords: device tracker,bluetooth classic,home assistant,raspberry pi,mqtt
Classifier: Programming Language :: Python :: 3.11
Classifier: Programming Language :: Python :: 3.12
Classifier: Typing :: Typed
Classifier: License :: OSI Approved :: MIT License
Classifier: Operating System :: POSIX :: Linux
Requires-Python: >=3.11
License-File: LICENSE
Requires-Dist: paho-mqtt ==2.1.*
Requires-Dist: requests ==2.32.*
Provides-Extra: dev
Requires-Dist: pre-commit ; extra == 'dev'
Requires-Dist: tox ; extra == 'dev'
Requires-Dist: sphinx ; extra == 'dev'
Requires-Dist: sphinx-rtd-theme ; extra == 'dev'
Requires-Dist: sphinx-copybutton ; extra == 'dev'
